{"path":"_samples/fortune-marissa-mayer-baby-is-easy-yahoos-fun.md","title":"Marissa Mayer: Baby is easy, Yahoo's fun","excerpt":"Yahoo CEO Marissa Mayer says having a new baby is way easier than people made it out to be.","sourceUrl":"https://everyday-cc.github.io/dei/api/samples/fortune-marissa-mayer-baby-is-easy-yahoos-fun/index.json","webUrl":"https://everyday.cc/dei/sample/fortune-marissa-mayer-baby-is-easy-yahoos-fun/","originalUrl":"https://youtube.com/watch?v=ZExA0kud9a8","provider":{"name":"Fortune","domain":"fortune.com","images":[{"url":"https://everyday-cc.github.io/dei/assets/images/organizations/fortune.com-50x50.jpg","width":50,"height":50,"title":null,"attribution":null,"isCached":false}],"publishers":null,"authors":null},"featuredContent":"<iframe width=\"800\" height=\"500\" frameborder=\"0\" src=\"https://www.youtube.com/embed/ZExA0kud9a8\" allow=\"accelerometer; autoplay; encrypted-media; gyroscope; picture-in-picture\" allowfullscreen></iframe>","actions":null,"publishedDateTime":"2012-11-29T11:34:30-08:00","topItems":null,"size":null,"heat":51,"tags":null,"images":[{"url":"https://i.ytimg.com/vi/ZExA0kud9a8/hqdefault.jpg","width":480,"height":360,"title":null,"attribution":null,"isCached":true}],"content":"\r\n","type":"video","topics":["DEI","Women in the Workplace"]}